{
  "last_update": "2026-01-21",
  "manresIA_content": {
    "word_of_the_day": {
        "word": "punxir",
        "definition": "Variant local del verb punxar, utilitzada genuïnament a la comarca del Bages.",
        "example": "Vigila amb l'esbarzer, que et punixiràs!",
        "agent_tifa": "Punxir... l'únic que punxeu vosaltres són les rodes dels cotxes que aparquen malament al Passeig. Aneu a pastar fang!"
    },
    "smart_city_news": "L'Ajuntament de Manresa utilitza sensors d'IA per gestionar els fluxos de turistes a la Seu.",
    "history_snippet": "Segons El Pou de la Gallina, el barri vell és el testimoni de la resiliència de la ciutat."
  }
}
